azure_voice_list/__init__.py
azure_voice_list/main.py
azure_voice_list-0.1.0.dist-info/METADATA
azure_voice_list-0.1.0.dist-info/WHEEL
azure_voice_list-0.1.0.dist-info/entry_points.txt
azure_voice_list-0.1.0.dist-info/licenses/LICENSE
azure_voice_list-0.1.0.dist-info/RECORD
