Metadata-Version: 2.3
Name: azure_voice_list
Version: 0.1.0
Summary: A package to retrieve available voices from Azure Cognitive Services Speech SDK.
Project-URL: Homepage, https://github.com/BlueBirdBack/azure_voice_list
Project-URL: Repository, https://github.com/BlueBirdBack/azure_voice_list
Author-email: BlueBirdBack <avery@bluebirdback.com>
Maintainer-email: BlueBirdBack <avery@bluebirdback.com>
License: MIT
License-File: LICENSE
Keywords: azure,cognitive services,sdk,speech,voice
Classifier: Intended Audience :: Developers
Classifier: License :: OSI Approved :: MIT License
Classifier: Operating System :: OS Independent
Classifier: Programming Language :: Python :: 3
Classifier: Programming Language :: Python :: 3.7
Classifier: Programming Language :: Python :: 3.8
Classifier: Programming Language :: Python :: 3.9
Classifier: Programming Language :: Python :: 3.10
Classifier: Topic :: Software Development :: Libraries
Classifier: Topic :: Utilities
Requires-Python: >=3.7
Requires-Dist: azure-cognitiveservices-speech
Requires-Dist: python-dotenv
